pwntools_r2/__init__.py
pwntools_r2-1.3.3.8.data/scripts/pwntools-gdb
pwntools_r2-1.3.3.8.dist-info/METADATA
pwntools_r2-1.3.3.8.dist-info/WHEEL
pwntools_r2-1.3.3.8.dist-info/top_level.txt
pwntools_r2-1.3.3.8.dist-info/RECORD
