Metadata-Version: 2.1
Name: pwntools-r2
Version: 1.3.3.8
Summary: Debug exploits like a boss with Radare2 in pwntools
Home-page: https://github.com/ps1337/pwntools_r2
Author: ps1337 / @CaptnBanana
Author-email: ps1337@mailbox.org
License: UNKNOWN
Platform: UNKNOWN
Classifier: Programming Language :: Python :: 2
Classifier: License :: OSI Approved :: MIT License
Classifier: Operating System :: OS Independent
Requires-Dist: r2pipe
Requires-Dist: pwntools
